PyRunbookManager/PyRunbookManager.py
PyRunbookManager/__init__.py
PyRunbookManager-0.0.2.dist-info/LICENSE
PyRunbookManager-0.0.2.dist-info/METADATA
PyRunbookManager-0.0.2.dist-info/WHEEL
PyRunbookManager-0.0.2.dist-info/top_level.txt
PyRunbookManager-0.0.2.dist-info/RECORD
