Metadata-Version: 2.1
Name: PyRunbookManager
Version: 0.0.2
Summary: Easily install modules in azure automation runbooks.
Home-page: UNKNOWN
Author: ikbendion (dblonk)
Author-email: <contact@ikbendion.nl>
License: Apache 2.0
Project-URL: Source, https://github.com/ikbendion/PyRunbookManager
Keywords: python,azure,automation,runbooks,pip,dependencies
Platform: UNKNOWN
Classifier: Development Status :: 1 - Planning
Classifier: Intended Audience :: Developers
Classifier: Programming Language :: Python :: 3
Classifier: Operating System :: Unix
License-File: LICENSE
Requires-Dist: requests
